{
  "ret": "0",
  "msg": "ok",
  "sandbox": "false",
  "serverTime": 1598209752,
  "data": {
    "list": {
      "growup": [
        {
          "iruleId": 100015,
          "iladderStatus": "0",
          "iSort": "0",
          "sladderup": "",
          "sladderdown": "",
          "itopType": "2",
          "sTask": "首次晒单",
          "sTaskDesc": "成功下单后，首次晒单到道聚城动态",
          "sTaskDirec": "",
          "sPic": "http://shp.qpic.cn/daoju_album_pic/0/240518174527092_1490250550442/0",
          "sBtnDesc": "去完成",
          "sBtnType": "2",
          "sBtnHref": "tencent-daojucheng://my_order_list",
          "sReward": [
            {
              "rewardId": "1",
              "rewardName": "聚豆",
              "rewardIcon": "http://ossweb-img.qq.com/images/gameshop/aba/images/thumb_sPackageGoodsPic12529/judouxiaotu.png",
              "num": "2",
              "giftid": 0
            }
          ],
          "iCompleteNum": "1",
          "iroleinfo": "0",
          "dtStart": "2017-03-21 00:00:00",
          "iTaskType": "1",
          "iCurrentNum": 0,
          "iStatus": 0,
          "isNew": 0,
          "task_status": 50
        },
        {
          "iruleId": 100065,
          "iladderStatus": "0",
          "iSort": "0",
          "sladderup": "",
          "sladderdown": "",
          "itopType": "2",
          "sTask": "首次购买游戏周边商品",
          "sTaskDesc": "仅限掌上道聚城APP的周边商城",
          "sTaskDirec": "首次在APP的周边商城成功支付1笔订单",
          "sPic": "http://shp.qpic.cn/daoju_album_pic/0/240518174527092_1499677174580/0",
          "sBtnDesc": "去完成",
          "sBtnType": "2",
          "sBtnHref": "tencent-daojucheng://webpage?url=https%3a%2f%2fm.mall.qq.com%2f%23%2f",
          "sReward": [
            {
              "rewardId": "1",
              "rewardName": "聚豆",
              "rewardIcon": "http://ossweb-img.qq.com/images/gameshop/aba/images/thumb_sPackageGoodsPic12529/judouxiaotu.png",
              "num": "5",
              "giftid": 0
            }
          ],
          "iCompleteNum": "1",
          "iroleinfo": "0",
          "dtStart": "0000-00-00 00:00:00",
          "iTaskType": "1",
          "iCurrentNum": 0,
          "iStatus": 0,
          "isNew": 0,
          "task_status": 50
        },
        {
          "iruleId": 100068,
          "iladderStatus": "0",
          "iSort": "0",
          "sladderup": "",
          "sladderdown": "",
          "itopType": "2",
          "sTask": "【新手】首次购买手游道具",
          "sTaskDesc": "首次在APP内成功支付1笔手游订单",
          "sTaskDirec": "首次在APP内成功支付1笔手游订单（不包括支付聚豆）",
          "sPic": "http://shp.qpic.cn/daoju_album_pic/0/240518174527092_1499677054642/0",
          "sBtnDesc": "去完成",
          "sBtnType": "2",
          "sBtnHref": "tencent-daojucheng://alert?title=%E6%B8%A9%E9%A6%A8%E6%8F%90%E7%A4%BA&msg=%E8%AF%B7%E8%87%B3%E6%B8%B8%E6%88%8F%E5%88%86%E5%95%86%E5%9F%8E%E8%B4%AD%E4%B9%B0",
          "sReward": [
            {
              "rewardId": "1",
              "rewardName": "聚豆",
              "rewardIcon": "http://shp.qpic.cn/daoju_album_pic/0/240518174527092_1482388841252/0",
              "num": "5",
              "giftid": 0
            }
          ],
          "iCompleteNum": "1",
          "iroleinfo": "0",
          "dtStart": "0000-00-00 00:00:00",
          "iTaskType": "1",
          "iCurrentNum": 0,
          "iStatus": 0,
          "isNew": 0,
          "task_status": 50
        },
        {
          "iruleId": "263783",
          "iladderStatus": "0",
          "iSort": "0",
          "sladderup": "",
          "sladderdown": "",
          "itopType": "2",
          "sTask": "【心悦】每周累计完成10笔订单",
          "sTaskDesc": "心悦成长值需要达到10000以上",
          "sTaskDirec": "包括Q币、人民币、点券支付；包括在PC商城、PC活动、掌上道聚城商城、掌上道聚城H5活动和周边商城；包括我的订单和赠送订单",
          "sPic": "http://shp.qpic.cn/daoju_album_pic/0/240518174527092_1592372009356/0",
          "sBtnDesc": "去完成",
          "sBtnType": "2",
          "sBtnHref": "tencent-daojucheng://alert?title=%E6%B8%A9%E9%A6%A8%E6%8F%90%E7%A4%BA&msg=%E8%AF%B7%E8%87%B3%E6%B8%B8%E6%88%8F%E5%88%86%E5%95%86%E5%9F%8E%E8%B4%AD%E4%B9%B0",
          "sReward": [
            {
              "rewardId": "1",
              "rewardName": "聚豆",
              "rewardIcon": "http://ossweb-img.qq.com/images/gameshop/aba/images/thumb_sPackageGoodsPic12529/judouxiaotu.png",
              "num": "30",
              "giftid": 0
            },
            {
              "rewardId": "19",
              "rewardName": "心悦成长值",
              "rewardIcon": "http://shp.qpic.cn/daoju_album_pic/0/240518174527092_1483496021459/0",
              "num": "50",
              "giftid": 0
            }
          ],
          "iCompleteNum": "10",
          "iroleinfo": "0",
          "dtStart": "0000-00-00 00:00:00",
          "iTaskType": "3",
          "iCurrentNum": 0,
          "iStatus": 0,
          "isNew": 0,
          "task_status": 50
        },
        {
          "iruleId": "263400",
          "iladderStatus": "0",
          "iSort": "0",
          "sladderup": "",
          "sladderdown": "",
          "itopType": "2",
          "sTask": "【心悦】周周活动达人",
          "sTaskDesc": "心悦成长值需要达到10000以上",
          "sTaskDirec": "每周参与活动付费1次，仅限道聚城开发的活动，包含APP端和PC的活动",
          "sPic": "http://shp.qpic.cn/daoju_album_pic/0/240518174527092_1592372009356/0",
          "sBtnDesc": "去完成",
          "sBtnType": "2",
          "sBtnHref": "tencent-daojucheng://alert?title=%E6%B8%A9%E9%A6%A8%E6%8F%90%E7%A4%BA&msg=%E8%AF%B7%E8%87%B3%E6%B8%B8%E6%88%8F%E5%88%86%E5%95%86%E5%9F%8E%E5%8F%82%E4%B8%8E%E9%81%93%E8%81%9A%E5%9F%8E%E6%B4%BB%E5%8A%A8",
          "sReward": [
            {
              "rewardId": "1",
              "rewardName": "聚豆",
              "rewardIcon": "http://ossweb-img.qq.com/images/gameshop/aba/images/thumb_sPackageGoodsPic12529/judouxiaotu.png",
              "num": "5",
              "giftid": 0
            },
            {
              "rewardId": "19",
              "rewardName": "心悦成长值",
              "rewardIcon": "http://shp.qpic.cn/daoju_album_pic/0/240518174527092_1483496021459/0",
              "num": "15",
              "giftid": 0
            }
          ],
          "iCompleteNum": "1",
          "iroleinfo": "0",
          "dtStart": "0000-00-00 00:00:00",
          "iTaskType": "3",
          "iCurrentNum": 0,
          "iStatus": 0,
          "iReceive": 0,
          "dtComplete": "2020-07-02 00:46:10",
          "dtReceive": "2020-07-05 00:00:00",
          "dtDeadline": "2020-07-05 00:00:00",
          "dtCommit": "2020-07-05 00:00:00",
          "isNew": 0,
          "task_status": 50
        },
        {
          "iruleId": "263403",
          "iladderStatus": "0",
          "iSort": "0",
          "sladderup": "",
          "sladderdown": "",
          "itopType": "2",
          "sTask": "成为心悦VIP",
          "sTaskDesc": "30天内首次在道聚城购买过道具",
          "sTaskDirec": "心悦成长值需要达到50000以上；包含APP端和PC端，仅限一次",
          "sPic": "http://shp.qpic.cn/daoju_album_pic/0/240518174527092_1592372009356/0",
          "sBtnDesc": "去完成",
          "sBtnType": "2",
          "sBtnHref": "tencent-daojucheng://alert?title=%E6%B8%A9%E9%A6%A8%E6%8F%90%E7%A4%BA&msg=%E8%AF%B7%E8%87%B3%E6%B8%B8%E6%88%8F%E5%88%86%E5%95%86%E5%9F%8E%E8%B4%AD%E4%B9%B0",
          "sReward": [
            {
              "rewardId": "1",
              "rewardName": "聚豆",
              "rewardIcon": "http://ossweb-img.qq.com/images/gameshop/aba/images/thumb_sPackageGoodsPic12529/judouxiaotu.png",
              "num": "10",
              "giftid": 0
            },
            {
              "rewardId": "19",
              "rewardName": "心悦成长值",
              "rewardIcon": "http://shp.qpic.cn/daoju_album_pic/0/240518174527092_1483496021459/0",
              "num": "25",
              "giftid": 0
            }
          ],
          "iCompleteNum": "1",
          "iroleinfo": "0",
          "dtStart": "0000-00-00 00:00:00",
          "iTaskType": "1",
          "iCurrentNum": "22",
          "iStatus": 0,
          "iReceive": "0",
          "dtComplete": "2020-07-02 00:46:10",
          "dtReceive": "0000-00-00 00:00:00",
          "dtDeadline": "0000-00-00 00:00:00",
          "dtCommit": "2020-07-02 00:46:10",
          "isNew": 0,
          "task_status": 50
        },
        {
          "iruleId": "263404",
          "iladderStatus": "0",
          "iSort": "0",
          "sladderup": "",
          "sladderdown": "",
          "itopType": "2",
          "sTask": "【心悦】赠人玫瑰，手留余香",
          "sTaskDesc": "心悦成长值需要达到10000以上",
          "sTaskDirec": "每周赠送1次，包括给他们的许愿买单",
          "sPic": "http://shp.qpic.cn/daoju_album_pic/0/240518174527092_1592372009356/0",
          "sBtnDesc": "去完成",
          "sBtnType": "2",
          "sBtnHref": "tencent-daojucheng://alert?title=%E6%B8%A9%E9%A6%A8%E6%8F%90%E7%A4%BA&msg=%E8%AF%B7%E8%87%B3%E6%B8%B8%E6%88%8F%E5%88%86%E5%95%86%E5%9F%8E%E8%B5%A0%E9%80%81%EF%BD%9E",
          "sReward": [
            {
              "rewardId": "1",
              "rewardName": "聚豆",
              "rewardIcon": "http://ossweb-img.qq.com/images/gameshop/aba/images/thumb_sPackageGoodsPic12529/judouxiaotu.png",
              "num": "5",
              "giftid": 0
            },
            {
              "rewardId": "19",
              "rewardName": "心悦成长值",
              "rewardIcon": "http://shp.qpic.cn/daoju_album_pic/0/240518174527092_1483496021459/0",
              "num": "10",
              "giftid": 0
            }
          ],
          "iCompleteNum": "1",
          "iroleinfo": "0",
          "dtStart": "0000-00-00 00:00:00",
          "iTaskType": "3",
          "iCurrentNum": 0,
          "iStatus": 0,
          "iReceive": 0,
          "dtComplete": "2020-07-02 00:46:10",
          "dtReceive": "0000-00-00 00:00:00",
          "dtDeadline": "0000-00-00 00:00:00",
          "dtCommit": "2020-07-02 00:46:10",
          "isNew": 0,
          "task_status": 50
        },
        {
          "iruleId": "263406",
          "iladderStatus": "0",
          "iSort": "0",
          "sladderup": "",
          "sladderdown": "",
          "itopType": "2",
          "sTask": "【心悦】每周累计完成20笔订单\t",
          "sTaskDesc": "心悦成长值需要达到10000以上",
          "sTaskDirec": "包括Q币、人民币、点券支付；包括在PC商城、PC活动、掌上道聚城商城、掌上道聚城H5活动和周边商城；包括我的订单和赠送订单",
          "sPic": "http://shp.qpic.cn/daoju_album_pic/0/240518174527092_1592372009356/0",
          "sBtnDesc": "去完成",
          "sBtnType": "2",
          "sBtnHref": "tencent-daojucheng://alert?title=%E6%B8%A9%E9%A6%A8%E6%8F%90%E7%A4%BA&msg=%E8%AF%B7%E8%87%B3%E6%B8%B8%E6%88%8F%E5%88%86%E5%95%86%E5%9F%8E%E8%B4%AD%E4%B9%B0",
          "sReward": [
            {
              "rewardId": "1",
              "rewardName": "聚豆",
              "rewardIcon": "http://ossweb-img.qq.com/images/gameshop/aba/images/thumb_sPackageGoodsPic12529/judouxiaotu.png",
              "num": "30",
              "giftid": 0
            },
            {
              "rewardId": "19",
              "rewardName": "心悦成长值",
              "rewardIcon": "http://shp.qpic.cn/daoju_album_pic/0/240518174527092_1483496021459/0",
              "num": "50",
              "giftid": 0
            }
          ],
          "iCompleteNum": "20",
          "iroleinfo": "0",
          "dtStart": "0000-00-00 00:00:00",
          "iTaskType": "3",
          "iCurrentNum": 0,
          "iStatus": 0,
          "iReceive": 0,
          "dtComplete": "2020-07-02 00:46:10",
          "dtReceive": "0000-00-00 00:00:00",
          "dtDeadline": "0000-00-00 00:00:00",
          "dtCommit": "2020-07-02 00:46:10",
          "isNew": 0,
          "task_status": 50
        },
        {
          "iruleId": "263781",
          "iladderStatus": "0",
          "iSort": "0",
          "sladderup": "",
          "sladderdown": "",
          "itopType": "2",
          "sTask": "【心悦】单笔订单金额超过100元\t",
          "sTaskDesc": "心悦成长值需要达到10000以上",
          "sTaskDirec": "包括Q币、人民币、点券支付；包括在PC商城、PC活动、掌上道聚城商城、掌上道聚城H5活动和周边商城；包括我的订单和赠送订单",
          "sPic": "http://shp.qpic.cn/daoju_album_pic/0/240518174527092_1592372009356/0",
          "sBtnDesc": "去完成",
          "sBtnType": "2",
          "sBtnHref": "tencent-daojucheng://alert?title=%E6%B8%A9%E9%A6%A8%E6%8F%90%E7%A4%BA&msg=%E8%AF%B7%E8%87%B3%E6%B8%B8%E6%88%8F%E5%88%86%E5%95%86%E5%9F%8E%E8%B4%AD%E4%B9%B0",
          "sReward": [
            {
              "rewardId": "1",
              "rewardName": "聚豆",
              "rewardIcon": "http://ossweb-img.qq.com/images/gameshop/aba/images/thumb_sPackageGoodsPic12529/judouxiaotu.png",
              "num": "15",
              "giftid": 0
            },
            {
              "rewardId": "19",
              "rewardName": "心悦成长值",
              "rewardIcon": "http://shp.qpic.cn/daoju_album_pic/0/240518174527092_1483496021459/0",
              "num": "35",
              "giftid": 0
            }
          ],
          "iCompleteNum": "1",
          "iroleinfo": "0",
          "dtStart": "0000-00-00 00:00:00",
          "iTaskType": "1",
          "iCurrentNum": "0",
          "iStatus": 0,
          "iReceive": "0",
          "dtComplete": "2020-07-02 00:46:10",
          "dtReceive": "0000-00-00 00:00:00",
          "dtDeadline": "0000-00-00 00:00:00",
          "dtCommit": "2020-07-02 00:46:10",
          "isNew": 0,
          "task_status": 50
        },
        {
          "iruleId": "100010",
          "iladderStatus": "0",
          "iSort": "11",
          "sladderup": "100009",
          "sladderdown": "0",
          "itopType": "2",
          "sTask": "【新手】绑定手机号",
          "sTaskDesc": "绑定您的手机号",
          "sTaskDirec": "",
          "sPic": "http://shp.qpic.cn/daoju_album_pic/0/240518174527092_1482372138837/0",
          "sBtnDesc": "去完成",
          "sBtnType": "2",
          "sBtnHref": "tencent-daojucheng://account_bind",
          "sReward": [
            {
              "rewardId": "1",
              "rewardName": "聚豆",
              "rewardIcon": "http://ossweb-img.qq.com/images/gameshop/aba/images/thumb_sPackageGoodsPic12529/judouxiaotu.png",
              "num": "2",
              "giftid": 0
            }
          ],
          "iCompleteNum": "1",
          "iroleinfo": "0",
          "dtStart": "0000-00-00 00:00:00",
          "iTaskType": "1",
          "iCurrentNum": "0",
          "iStatus": 0,
          "iReceive": "0",
          "dtComplete": "2019-02-13 12:28:01",
          "dtReceive": "0000-00-00 00:00:00",
          "dtDeadline": "0000-00-00 00:00:00",
          "dtCommit": "2019-02-13 12:28:01",
          "isNew": 0,
          "task_status": 61
        },
        {
          "iruleId": "327094",
          "iladderStatus": "0",
          "iSort": "12",
          "sladderup": "",
          "sladderdown": "0",
          "itopType": "2",
          "sTask": "【新手】活动订阅",
          "sTaskDesc": "至少订阅一个游戏的活动信息",
          "sTaskDirec": "订阅后，会在消息中收到该游戏的活动提醒",
          "sPic": "http://shp.qpic.cn/daoju_album_pic/0/240518174527092_1482310891713/0",
          "sBtnDesc": "去完成",
          "sBtnType": "2",
          "sBtnHref": "tencent-daojucheng://weex?weex_id=44",
          "sReward": [
            {
              "rewardId": "1",
              "rewardName": "聚豆",
              "rewardIcon": "http://ossweb-img.qq.com/images/gameshop/aba/images/thumb_sPackageGoodsPic12529/judouxiaotu.png",
              "num": "1",
              "giftid": 0
            }
          ],
          "iCompleteNum": "1",
          "iroleinfo": "0",
          "dtStart": "0000-00-00 00:00:00",
          "iTaskType": "1",
          "iCurrentNum": 0,
          "iStatus": 0,
          "isNew": 0,
          "task_status": 62
        },
        {
          "iruleId": "201422",
          "iladderStatus": "0",
          "iSort": "15",
          "sladderup": "",
          "sladderdown": "0",
          "itopType": "2",
          "sTask": "【新手】首次购买端游道具",
          "sTaskDesc": "首次在APP内成功支付1笔端游订单",
          "sTaskDirec": "在APP内首次成功支付一笔订单（不包括支付聚豆）",
          "sPic": "http://shp.qpic.cn/daoju_album_pic/0/240518174527092_1499677279810/0",
          "sBtnDesc": "去完成",
          "sBtnType": "2",
          "sBtnHref": "tencent-daojucheng://alert?title=%E6%B8%A9%E9%A6%A8%E6%8F%90%E7%A4%BA&msg=%E8%AF%B7%E8%87%B3%E6%B8%B8%E6%88%8F%E5%88%86%E5%95%86%E5%9F%8E%E8%B4%AD%E4%B9%B0",
          "sReward": [
            {
              "rewardId": "1",
              "rewardName": "聚豆",
              "rewardIcon": "http://ossweb-img.qq.com/images/gameshop/aba/images/thumb_sPackageGoodsPic12529/judouxiaotu.png",
              "num": "5",
              "giftid": 0
            },
            {
              "rewardId": "3",
              "rewardName": "么么哒",
              "rewardIcon": "http://ossweb-img.qq.com/images/daoju/dbm/gift/20161227_7677.png",
              "num": "1",
              "giftid": "2"
            }
          ],
          "iCompleteNum": "1",
          "iroleinfo": "0",
          "dtStart": "0000-00-00 00:00:00",
          "iTaskType": "1",
          "iCurrentNum": "0",
          "iStatus": 0,
          "iReceive": "0",
          "dtComplete": "2019-02-13 12:28:01",
          "dtReceive": "0000-00-00 00:00:00",
          "dtDeadline": "0000-00-00 00:00:00",
          "dtCommit": "2019-02-13 12:28:01",
          "isNew": 0,
          "task_status": 65
        },
        {
          "iruleId": "100058",
          "iladderStatus": "0",
          "iSort": "0",
          "sladderup": "",
          "sladderdown": "",
          "itopType": "2",
          "sTask": "首次绑定微信号",
          "sTaskDesc": "畅游手游商城，领海量礼包",
          "sTaskDirec": "仅限APP 2.9.0及以上版本的用户完成任务",
          "sPic": "http://shp.qpic.cn/daoju_album_pic/0/240518174527092_1493727820611/0",
          "sBtnDesc": "已完成",
          "sBtnType": "2",
          "sBtnHref": "tencent-daojucheng://account_bind",
          "sReward": [
            {
              "rewardId": "1",
              "rewardName": "聚豆",
              "rewardIcon": "http://ossweb-img.qq.com/images/gameshop/aba/images/thumb_sPackageGoodsPic12529/judouxiaotu.png",
              "num": "8",
              "giftid": 0
            },
            {
              "rewardId": "3",
              "rewardName": "老司机",
              "rewardIcon": "http://ossweb-img.qq.com/images/daoju/dbm/gift/20161227_8728.png",
              "num": "1",
              "giftid": "3"
            }
          ],
          "iCompleteNum": "1",
          "iroleinfo": "0",
          "dtStart": "0000-00-00 00:00:00",
          "iTaskType": "1",
          "iCurrentNum": "1",
          "iStatus": 1,
          "iReceive": "1",
          "dtComplete": "2019-02-13 12:34:01",
          "dtReceive": "2019-02-13 00:00:00",
          "dtDeadline": "0000-00-00 00:00:00",
          "dtCommit": "2019-02-13 12:34:06",
          "isNew": 0,
          "task_status": 100
        },
        {
          "iruleId": "201679",
          "iladderStatus": "0",
          "iSort": "0",
          "sladderup": "",
          "sladderdown": "",
          "itopType": "2",
          "sTask": "【新手】完善资料",
          "sTaskDesc": "完善个人资料",
          "sTaskDirec": "",
          "sPic": "http://shp.qpic.cn/daoju_album_pic/0/240518174527092_1592371975957/0",
          "sBtnDesc": "已完成",
          "sBtnType": "2",
          "sBtnHref": "tencent-daojucheng://PersonInfoEdit",
          "sReward": [
            {
              "rewardId": "1",
              "rewardName": "聚豆",
              "rewardIcon": "http://shp.qpic.cn/daoju_album_pic/0/240518174527092_1482841230769/0",
              "num": "5",
              "giftid": 0
            }
          ],
          "iCompleteNum": "1",
          "iroleinfo": "0",
          "dtStart": "0000-00-00 00:00:00",
          "iTaskType": "1",
          "iCurrentNum": "1",
          "iStatus": 1,
          "iReceive": "1",
          "dtComplete": "2020-08-05 22:57:06",
          "dtReceive": "2020-08-05 00:00:00",
          "dtDeadline": "0000-00-00 00:00:00",
          "dtCommit": "2020-08-05 22:57:10",
          "isNew": 0,
          "task_status": 100
        },
        {
          "iruleId": "100035",
          "iladderStatus": "0",
          "iSort": "3",
          "sladderup": "",
          "sladderdown": "",
          "itopType": "2",
          "sTask": "我很满意",
          "sTaskDesc": "给三条资讯内容点赞",
          "sTaskDirec": "",
          "sPic": "http://shp.qpic.cn/daoju_album_pic/0/240518174527092_1482310487402/0",
          "sBtnDesc": "已完成",
          "sBtnType": "2",
          "sBtnHref": "tencent-daojucheng://tab?id=discover",
          "sReward": [
            {
              "rewardId": "1",
              "rewardName": "聚豆",
              "rewardIcon": "http://ossweb-img.qq.com/images/gameshop/aba/images/thumb_sPackageGoodsPic12529/judouxiaotu.png",
              "num": "10",
              "giftid": 0
            },
            {
              "rewardId": "3",
              "rewardName": "血瓶",
              "rewardIcon": "http://ossweb-img.qq.com/images/daoju/dbm/gift/20161227_7513.png",
              "num": "3",
              "giftid": "1"
            }
          ],
          "iCompleteNum": "3",
          "iroleinfo": "0",
          "dtStart": "0000-00-00 00:00:00",
          "iTaskType": "1",
          "iCurrentNum": "3",
          "iStatus": 1,
          "iReceive": "1",
          "dtComplete": "2020-05-03 00:55:02",
          "dtReceive": "2020-05-03 00:00:00",
          "dtDeadline": "0000-00-00 00:00:00",
          "dtCommit": "2020-05-03 00:56:02",
          "isNew": 0,
          "task_status": 103
        },
        {
          "iruleId": "201266",
          "iladderStatus": "0",
          "iSort": "8",
          "sladderup": "",
          "sladderdown": "302128",
          "itopType": "2",
          "sTask": "【新手】Hello，道聚城",
          "sTaskDesc": "下载并登陆掌上道聚城",
          "sTaskDirec": "",
          "sPic": "http://shp.qpic.cn/daoju_album_pic/0/240518174527092_1482310703277/0",
          "sBtnDesc": "已完成",
          "sBtnType": "2",
          "sBtnHref": "",
          "sReward": [
            {
              "rewardId": "1",
              "rewardName": "聚豆",
              "rewardIcon": "http://ossweb-img.qq.com/images/gameshop/aba/images/thumb_sPackageGoodsPic12529/judouxiaotu.png",
              "num": "3",
              "giftid": 0
            },
            {
              "rewardId": "3",
              "rewardName": "血瓶",
              "rewardIcon": "http://ossweb-img.qq.com/images/daoju/dbm/gift/20161227_7513.png",
              "num": "1",
              "giftid": "1"
            }
          ],
          "iCompleteNum": "1",
          "iroleinfo": "0",
          "dtStart": "0000-00-00 00:00:00",
          "iTaskType": "1",
          "iCurrentNum": "1",
          "iStatus": 1,
          "iReceive": "1",
          "dtComplete": "2019-02-13 12:27:41",
          "dtReceive": "2019-02-13 00:00:00",
          "dtDeadline": "0000-00-00 00:00:00",
          "dtCommit": "2019-02-13 12:28:37",
          "isNew": 0,
          "task_status": 108
        },
        {
          "iruleId": "302128",
          "iladderStatus": "1",
          "iSort": "9",
          "sladderup": "201266",
          "sladderdown": "100009",
          "itopType": "2",
          "sTask": "【新手】绑定角色",
          "sTaskDesc": "至少绑定一个游戏角色",
          "sTaskDirec": "",
          "sPic": "http://shp.qpic.cn/daoju_album_pic/0/240518174527092_1482309361928/0",
          "sBtnDesc": "已完成",
          "sBtnType": "2",
          "sBtnHref": "tencent-daojucheng://webpage?url=https%3A%2F%2Fapp.daoju.qq.com%2Ftask%2Fapp%2Fbd.html",
          "sReward": [
            {
              "rewardId": "1",
              "rewardName": "聚豆",
              "rewardIcon": "http://ossweb-img.qq.com/images/gameshop/aba/images/thumb_sPackageGoodsPic12529/judouxiaotu.png",
              "num": "2",
              "giftid": 0
            }
          ],
          "iCompleteNum": "1",
          "iroleinfo": "0",
          "dtStart": "2016-12-09 00:00:00",
          "iTaskType": "1",
          "iCurrentNum": "1",
          "iStatus": 1,
          "iReceive": "1",
          "dtComplete": "2019-02-13 12:27:54",
          "dtReceive": "2019-02-13 00:00:00",
          "dtDeadline": "0000-00-00 00:00:00",
          "dtCommit": "2020-08-24 00:58:48",
          "sladderdownDesc": {
            "sTask": "【新手】上传头像",
            "sTaskDesc": "上传一张您的头像"
          },
          "isNew": 0,
          "task_status": 109
        },
        {
          "iruleId": "100009",
          "iladderStatus": "0",
          "iSort": "10",
          "sladderup": "302128",
          "sladderdown": "100010",
          "itopType": "2",
          "sTask": "【新手】上传头像",
          "sTaskDesc": "上传一张您的头像",
          "sTaskDirec": "没有王道，怎么出来混啊",
          "sPic": "http://shp.qpic.cn/daoju_album_pic/0/240518174527092_1482311222739/0",
          "sBtnDesc": "已完成",
          "sBtnType": "2",
          "sBtnHref": "tencent-daojucheng://PersonInfoEdit",
          "sReward": [
            {
              "rewardId": "1",
              "rewardName": "聚豆",
              "rewardIcon": "http://ossweb-img.qq.com/images/gameshop/aba/images/thumb_sPackageGoodsPic12529/judouxiaotu.png",
              "num": "3",
              "giftid": 0
            }
          ],
          "iCompleteNum": "1",
          "iroleinfo": "0",
          "dtStart": "0000-00-00 00:00:00",
          "iTaskType": "1",
          "iCurrentNum": "1",
          "iStatus": 1,
          "iReceive": "1",
          "dtComplete": "2019-02-13 12:34:41",
          "dtReceive": "2019-02-13 00:00:00",
          "dtDeadline": "0000-00-00 00:00:00",
          "dtCommit": "2019-02-13 12:34:43",
          "isNew": 0,
          "task_status": 110
        },
        {
          "iruleId": "302139",
          "iladderStatus": "0",
          "iSort": "14",
          "sladderup": "",
          "sladderdown": "0",
          "itopType": "2",
          "sTask": "【新手】首次许愿",
          "sTaskDesc": "第一次发布道具许愿",
          "sTaskDirec": "人没有梦想，和咸鱼有什么区别！",
          "sPic": "http://shp.qpic.cn/daoju_album_pic/0/240518174527092_1482310418738/0",
          "sBtnDesc": "已完成",
          "sBtnType": "2",
          "sBtnHref": "tencent-daojucheng://wish_list?biz=lol",
          "sReward": [
            {
              "rewardId": "1",
              "rewardName": "聚豆",
              "rewardIcon": "http://ossweb-img.qq.com/images/gameshop/aba/images/thumb_sPackageGoodsPic12529/judouxiaotu.png",
              "num": "1",
              "giftid": 0
            }
          ],
          "iCompleteNum": "1",
          "iroleinfo": "0",
          "dtStart": "0000-00-00 00:00:00",
          "iTaskType": "1",
          "iCurrentNum": "1",
          "iStatus": 1,
          "iReceive": "1",
          "dtComplete": "2019-02-13 12:32:54",
          "dtReceive": "2019-02-13 00:00:00",
          "dtDeadline": "0000-00-00 00:00:00",
          "dtCommit": "2020-08-23 07:24:29",
          "isNew": 0,
          "task_status": 114
        }
      ],
      "day": [
        {
          "iruleId": "327097",
          "iladderStatus": "0",
          "iSort": "0",
          "sladderup": "",
          "sladderdown": "",
          "itopType": "1",
          "sTask": "在世神灯",
          "sTaskDesc": "为他人的许愿买单",
          "sTaskDirec": "为他人或者好友的许愿买单",
          "sPic": "http://shp.qpic.cn/daoju_album_pic/0/240518174527092_1592371955528/0",
          "sBtnDesc": "去完成",
          "sBtnType": "2",
          "sBtnHref": "tencent-daojucheng://weex?weex_id=71",
          "sReward": [
            {
              "rewardId": "1",
              "rewardName": "聚豆",
              "rewardIcon": "http://ossweb-img.qq.com/images/gameshop/aba/images/thumb_sPackageGoodsPic12529/judouxiaotu.png",
              "num": "5",
              "giftid": 0
            },
            {
              "rewardId": "2",
              "rewardName": "活跃度",
              "rewardIcon": "http://shp.qpic.cn/daoju_album_pic/0/240518174527092_1482841236330/0",
              "num": "20",
              "giftid": 0
            }
          ],
          "iCompleteNum": "1",
          "iroleinfo": "0",
          "dtStart": "0000-00-00 00:00:00",
          "iTaskType": "2",
          "iCurrentNum": 0,
          "iStatus": 0,
          "iReceive": 0,
          "dtComplete": "2020-07-02 00:46:10",
          "dtReceive": "0000-00-00 00:00:00",
          "dtDeadline": "0000-00-00 00:00:00",
          "dtCommit": "2020-07-02 00:46:10",
          "isNew": 0,
          "task_status": 50
        },
        {
          "iruleId": "302124",
          "iladderStatus": "0",
          "iSort": "4",
          "sladderup": "",
          "sladderdown": "0",
          "itopType": "1",
          "sTask": "有理想",
          "sTaskDesc": "完成1次道具许愿",
          "sTaskDirec": "",
          "sPic": "http://shp.qpic.cn/daoju_album_pic/0/240518174527092_1482311448278/0",
          "sBtnDesc": "去完成",
          "sBtnType": "2",
          "sBtnHref": "tencent-daojucheng://wish_list?biz=dj",
          "sReward": [
            {
              "rewardId": "1",
              "rewardName": "聚豆",
              "rewardIcon": "http://ossweb-img.qq.com/images/gameshop/aba/images/thumb_sPackageGoodsPic12529/judouxiaotu.png",
              "num": "3",
              "giftid": 0
            },
            {
              "rewardId": "2",
              "rewardName": "活跃度",
              "rewardIcon": "http://shp.qpic.cn/daoju_album_pic/0/240518174527092_1482841236330/0",
              "num": "15",
              "giftid": 0
            }
          ],
          "iCompleteNum": "1",
          "iroleinfo": "0",
          "dtStart": "0000-00-00 00:00:00",
          "iTaskType": "2",
          "iCurrentNum": 0,
          "iStatus": 0,
          "iReceive": 0,
          "dtComplete": "2020-08-23 07:24:29",
          "dtReceive": "2020-08-23 00:00:00",
          "dtDeadline": "2020-08-23 00:00:00",
          "dtCommit": "2020-08-23 07:26:32",
          "isNew": 0,
          "task_status": 54
        },
        {
          "iruleId": 100007,
          "iladderStatus": "0",
          "iSort": "6",
          "sladderup": "",
          "sladderdown": "0",
          "itopType": "1",
          "sTask": "剁手达人",
          "sTaskDesc": "成功支付一笔5元或5元以上的订单",
          "sTaskDirec": "包括“我的订单”中的道具订单和赠送订单",
          "sPic": "http://shp.qpic.cn/daoju_album_pic/0/240518174527092_1482310743785/0",
          "sBtnDesc": "去完成",
          "sBtnType": "2",
          "sBtnHref": "tencent-daojucheng://alert?title=%E6%B8%A9%E9%A6%A8%E6%8F%90%E7%A4%BA&msg=%E8%AF%B7%E8%87%B3%E6%B8%B8%E6%88%8F%E5%88%86%E5%95%86%E5%9F%8E%E8%B4%AD%E4%B9%B0",
          "sReward": [
            {
              "rewardId": "1",
              "rewardName": "聚豆",
              "rewardIcon": "http://ossweb-img.qq.com/images/gameshop/aba/images/thumb_sPackageGoodsPic12529/judouxiaotu.png",
              "num": "3",
              "giftid": 0
            },
            {
              "rewardId": "2",
              "rewardName": "活跃度",
              "rewardIcon": "http://shp.qpic.cn/daoju_album_pic/0/240518174527092_1482841236330/0",
              "num": "20",
              "giftid": 0
            }
          ],
          "iCompleteNum": "1",
          "iroleinfo": "0",
          "dtStart": "0000-00-00 00:00:00",
          "iTaskType": "2",
          "iCurrentNum": 0,
          "iStatus": 0,
          "isNew": 0,
          "task_status": 56
        },
        {
          "iruleId": "100066",
          "iladderStatus": "0",
          "iSort": "0",
          "sladderup": "",
          "sladderdown": "",
          "itopType": "1",
          "sTask": "礼包达人",
          "sTaskDesc": "每日领取1个手游礼包",
          "sTaskDirec": "请将APP首页切换到手游，在首页的礼包中心领取；请下载APP最新版本领取礼包。",
          "sPic": "http://shp.qpic.cn/daoju_album_pic/0/240518174527092_1498099639755/0",
          "sBtnDesc": "已完成",
          "sBtnType": "2",
          "sBtnHref": "tencent-daojucheng://weex?weex_id=3&is_show_footer=0&is_show_mobileTab=1",
          "sReward": [
            {
              "rewardId": "1",
              "rewardName": "聚豆",
              "rewardIcon": "http://ossweb-img.qq.com/images/gameshop/aba/images/thumb_sPackageGoodsPic12529/judouxiaotu.png",
              "num": "3",
              "giftid": 0
            },
            {
              "rewardId": "2",
              "rewardName": "活跃度",
              "rewardIcon": "http://shp.qpic.cn/daoju_album_pic/0/240518174527092_1482841236330/0",
              "num": "20",
              "giftid": 0
            }
          ],
          "iCompleteNum": "1",
          "iroleinfo": "0",
          "dtStart": "0000-00-00 00:00:00",
          "iTaskType": "2",
          "iCurrentNum": "1",
          "iStatus": 1,
          "iReceive": "1",
          "dtComplete": "2020-08-24 00:58:49",
          "dtReceive": "2020-08-24 00:00:00",
          "dtDeadline": "2020-08-24 00:00:00",
          "dtCommit": "2020-08-24 01:18:21",
          "isNew": 0,
          "task_status": 100
        },
        {
          "iruleId": "100040",
          "iladderStatus": "0",
          "iSort": "1",
          "sladderup": "",
          "sladderdown": "",
          "itopType": "1",
          "sTask": "绝不错亿",
          "sTaskDesc": "浏览“活动中心”，防止错过亿万好礼！",
          "sTaskDirec": "",
          "sPic": "http://shp.qpic.cn/daoju_album_pic/0/240518174527092_1565593067735/0",
          "sBtnDesc": "已完成",
          "sBtnType": "2",
          "sBtnHref": "tencent-daojucheng://weex?weex_id=44",
          "sReward": [
            {
              "rewardId": "1",
              "rewardName": "聚豆",
              "rewardIcon": "http://ossweb-img.qq.com/images/gameshop/aba/images/thumb_sPackageGoodsPic12529/judouxiaotu.png",
              "num": "5",
              "giftid": 0
            },
            {
              "rewardId": "2",
              "rewardName": "活跃度",
              "rewardIcon": "http://shp.qpic.cn/daoju_album_pic/0/240518174527092_1482841236330/0",
              "num": "15",
              "giftid": 0
            },
            {
              "rewardId": "3",
              "rewardName": "血瓶",
              "rewardIcon": "http://ossweb-img.qq.com/images/daoju/dbm/gift/20161227_7513.png",
              "num": "1",
              "giftid": "1"
            }
          ],
          "iCompleteNum": "1",
          "iroleinfo": "0",
          "dtStart": "0000-00-00 00:00:00",
          "iTaskType": "2",
          "iCurrentNum": "1",
          "iStatus": 1,
          "iReceive": "1",
          "dtComplete": "2020-08-24 00:10:18",
          "dtReceive": "2020-08-24 00:00:00",
          "dtDeadline": "2020-08-24 00:00:00",
          "dtCommit": "2020-08-24 02:57:28",
          "isNew": 0,
          "task_status": 101
        },
        {
          "iruleId": "327091",
          "iladderStatus": "0",
          "iSort": "5",
          "sladderup": "",
          "sladderdown": "0",
          "itopType": "1",
          "sTask": "兑换有礼",
          "sTaskDesc": "在聚豆商城完成一次兑换或抽奖\t",
          "sTaskDirec": "包括参与道具兑换、道具抽奖和实物乐园",
          "sPic": "http://shp.qpic.cn/daoju_album_pic/0/240518174527092_1482310977093/0",
          "sBtnDesc": "已完成",
          "sBtnType": "2",
          "sBtnHref": "tencent-daojucheng://weex?weex_id=3",
          "sReward": [
            {
              "rewardId": "1",
              "rewardName": "聚豆",
              "rewardIcon": "http://ossweb-img.qq.com/images/gameshop/aba/images/thumb_sPackageGoodsPic12529/judouxiaotu.png",
              "num": "3",
              "giftid": 0
            },
            {
              "rewardId": "2",
              "rewardName": "活跃度",
              "rewardIcon": "http://shp.qpic.cn/daoju_album_pic/0/240518174527092_1482841236330/0",
              "num": "10",
              "giftid": 0
            }
          ],
          "iCompleteNum": "1",
          "iroleinfo": "0",
          "dtStart": "2016-12-09 23:54:46",
          "iTaskType": "2",
          "iCurrentNum": "1",
          "iStatus": 1,
          "iReceive": "1",
          "dtComplete": "2020-08-24 00:10:22",
          "dtReceive": "2020-08-24 00:00:00",
          "dtDeadline": "2020-08-24 00:00:00",
          "dtCommit": "2020-08-24 00:18:20",
          "isNew": 0,
          "task_status": 105
        }
      ],
      "game": null
    },
    "chest_list": {
      "100001": {
        "iruleId": "100001",
        "iCurrentNum": "45",
        "iCompleteNum": "20",
        "iStatus": "1",
        "iReceive": "1",
        "dtComplete": "2020-08-24 00:10:24",
        "dtReceive": "2020-08-24 00:00:00",
        "dtDeadline": "2020-08-24 00:00:00",
        "dtCommit": "2020-08-24 01:18:21",
        "iTaskType": "2",
        "iladderStatus": "0",
        "iSort": "0",
        "sladderup": "",
        "sladderdown": "0",
        "itopType": "4",
        "sTask": "活跃度银宝箱",
        "sTaskDesc": "日活跃度达到20点，可以打开宝箱。打开后有几率获得5-30聚豆。",
        "sTaskDirec": "日活跃度达到20点，可以打开宝箱。打开后有几率获得5-30聚豆。",
        "sPic": "http://shp.qpic.cn/daoju_album_pic/0/240518174527092_14813439109",
        "sBtnDesc": "去完成",
        "sBtnType": "1",
        "sBtnHref": "",
        "sReward": [
          {
            "rewardId": "2",
            "rewardName": "活跃度",
            "rewardIcon": "http://shp.qpic.cn/daoju_album_pic/0/240518174527092_1482841236330/0",
            "num": "1",
            "giftid": 0
          }
        ],
        "iroleinfo": "0",
        "dtStart": "0000-00-00 00:00:00"
      },
      "100002": {
        "iruleId": "100002",
        "iCurrentNum": "45",
        "iCompleteNum": "35",
        "iStatus": "1",
        "iReceive": "1",
        "dtComplete": "2020-08-24 01:18:21",
        "dtReceive": "2020-08-24 00:00:00",
        "dtDeadline": "2020-08-24 00:00:00",
        "dtCommit": "2020-08-24 01:18:24",
        "iTaskType": "2",
        "iladderStatus": "0",
        "iSort": "0",
        "sladderup": "100001",
        "sladderdown": "0",
        "itopType": "4",
        "sTask": "活跃度金宝箱",
        "sTaskDesc": "日活跃度达到35点，可以打开宝箱。打开后有几率获得10-60聚豆。",
        "sTaskDirec": "日活跃度达到35点，可以打开宝箱。打开后有几率获得10-60聚豆。",
        "sPic": "http://shp.qpic.cn/daoju_album_pic/0/240518174527092_14813510001",
        "sBtnDesc": "去完成",
        "sBtnType": "2",
        "sBtnHref": "",
        "sReward": [
          {
            "rewardId": "2",
            "rewardName": "活跃度",
            "rewardIcon": "http://shp.qpic.cn/daoju_album_pic/0/240518174527092_1482841236330/0",
            "num": "1",
            "giftid": 0
          }
        ],
        "iroleinfo": "0",
        "dtStart": "2016-12-10 00:00:00"
      }
    },
    "reddot": {
      "day": 0,
      "growup": 0,
      "game": 0
    }
  }
}